pydia2/__init__.py
pydia2/_dia.pyd
pydia2/cvconst.py
pydia2/lib/amd64/msdia140.dll
pydia2/lib/amd64/symsrv.dll
pydia2/lib/x86/msdia140.dll
pydia2/lib/x86/symsrv.dll
pydia2-0.2.1.dist-info/LICENSE
pydia2-0.2.1.dist-info/METADATA
pydia2-0.2.1.dist-info/WHEEL
pydia2-0.2.1.dist-info/top_level.txt
pydia2-0.2.1.dist-info/RECORD
