Metadata-Version: 2.1
Name: pydia2
Version: 0.2.1
Summary: DIA packaged for use without COM registration using comtypes
Home-page: https://github.com/segevfiner/pydia2
Author: Segev Finer
Author-email: segev208@gmail.com
License: MIT
Project-URL: Documentation, https://segevfiner.github.io/pydia2/
Project-URL: Issue Tracker, https://github.com/segevfiner/pydia2/issues
Keywords: dia,comtypes
Classifier: Development Status :: 3 - Alpha
Classifier: Environment :: Win32 (MS Windows)
Classifier: Intended Audience :: Developers
Classifier: Topic :: Software Development
Classifier: Topic :: Software Development :: Debuggers
Classifier: License :: OSI Approved :: MIT License
Classifier: Operating System :: Microsoft :: Windows
Classifier: Programming Language :: Python :: 3
Classifier: Programming Language :: Python :: 3.7
Classifier: Programming Language :: Python :: 3.8
Classifier: Programming Language :: Python :: 3.9
Classifier: Programming Language :: Python :: 3.10
Classifier: Programming Language :: Python :: 3.11
Classifier: Programming Language :: Python :: 3.12
Requires-Python: >=3.7
License-File: LICENSE
Requires-Dist: comtypes
Provides-Extra: dev
Requires-Dist: pycparser ; extra == 'dev'
Requires-Dist: sphinx ; extra == 'dev'
Requires-Dist: setuptools ; extra == 'dev'
